google/cloud/telcoautomation/__init__.py
google/cloud/telcoautomation/gapic_version.py
google/cloud/telcoautomation/py.typed
google/cloud/telcoautomation_v1/__init__.py
google/cloud/telcoautomation_v1/gapic_metadata.json
google/cloud/telcoautomation_v1/gapic_version.py
google/cloud/telcoautomation_v1/py.typed
google/cloud/telcoautomation_v1/services/__init__.py
google/cloud/telcoautomation_v1/services/telco_automation/__init__.py
google/cloud/telcoautomation_v1/services/telco_automation/async_client.py
google/cloud/telcoautomation_v1/services/telco_automation/client.py
google/cloud/telcoautomation_v1/services/telco_automation/pagers.py
google/cloud/telcoautomation_v1/services/telco_automation/transports/__init__.py
google/cloud/telcoautomation_v1/services/telco_automation/transports/base.py
google/cloud/telcoautomation_v1/services/telco_automation/transports/grpc.py
google/cloud/telcoautomation_v1/services/telco_automation/transports/grpc_asyncio.py
google/cloud/telcoautomation_v1/services/telco_automation/transports/rest.py
google/cloud/telcoautomation_v1/services/telco_automation/transports/rest_base.py
google/cloud/telcoautomation_v1/types/__init__.py
google/cloud/telcoautomation_v1/types/telcoautomation.py
google/cloud/telcoautomation_v1alpha1/__init__.py
google/cloud/telcoautomation_v1alpha1/gapic_metadata.json
google/cloud/telcoautomation_v1alpha1/gapic_version.py
google/cloud/telcoautomation_v1alpha1/py.typed
google/cloud/telcoautomation_v1alpha1/services/__init__.py
google/cloud/telcoautomation_v1alpha1/services/telco_automation/__init__.py
google/cloud/telcoautomation_v1alpha1/services/telco_automation/async_client.py
google/cloud/telcoautomation_v1alpha1/services/telco_automation/client.py
google/cloud/telcoautomation_v1alpha1/services/telco_automation/pagers.py
google/cloud/telcoautomation_v1alpha1/services/telco_automation/transports/__init__.py
google/cloud/telcoautomation_v1alpha1/services/telco_automation/transports/base.py
google_cloud_telcoautomation-0.4.0.dist-info/licenses/LICENSE
google_cloud_telcoautomation-0.4.0.dist-info/METADATA
google_cloud_telcoautomation-0.4.0.dist-info/WHEEL
google_cloud_telcoautomation-0.4.0.dist-info/top_level.txt
google_cloud_telcoautomation-0.4.0.dist-info/RECORD
